[
  {
    "image_name": "3205008_Invoice_77 (1).pdf"
  },
  {
    "image_name": "3205008_Invoice_77 (2).pdf"
  },
  {
    "image_name": "3205008_Invoice_77.pdf"
  },
  {
    "image_name": "3205008_jpeg.jpg"
  },
  {
    "image_name": "3205008_jpeg1.png"
  },
  {
    "image_name": "3205008_jpg.jpg"
  },
  {
    "image_name": "3205008_pngnew.jpg"
  },
  {
    "image_name": "3205008_Proforma_35 (1).pdf"
  },
  {
    "image_name": "3205008_Proforma_35.pdf"
  },
  {
    "image_name": "3205008_Proforma_36.pdf"
  },
  {
    "image_name": "3205008_Quotation_233 (2).pdf"
  },
  {
    "image_name": "3205008_Test scenario Master.xlsx"
  },
  {
    "image_name": "3205008_testcase-Teachernote and Notice (2).xlsx"
  },
  {
    "image_name": "3205008_abc.txt (2).txt"
  }
]